{
  "quiz": [
    {
      "question": "Какой жанр у 'Слова о полку Игореве'?",
      "options": [
        "роман",
        "былина",
        "воинская повесть",
        "поэма"
      ],
      "correctAnswer": "воинская повесть"
    },
    {
      "question": "Что такое IP-адрес?",
      "options": [
        "имя сайта",
        "уникальный номер устройства в сети",
        "пароль",
        "протокол"
      ],
      "correctAnswer": "уникальный номер устройства в сети"
    },
    {
      "question": "Какой самый распространённый металл в земной коре?",
      "options": [
        "железо",
        "медь",
        "алюминий",
        "кремний"
      ],
      "correctAnswer": "алюминий"
    },
    {
      "question": "Какой гормон регулирует сахар в крови?",
      "options": [
        "адреналин",
        "инсулин",
        "тироксин",
        "кортизол"
      ],
      "correctAnswer": "инсулин"
    },
    {
      "question": "Какой отдел мозга отвечает за координацию?",
      "options": [
        "кора",
        "мозжечок",
        "гипоталамус",
        "продолговатый"
      ],
      "correctAnswer": "мозжечок"
    },
    {
      "question": "Продолжите последовательность: 2, 6, 12, 20, ...",
      "options": [
        "24",
        "30",
        "36",
        "42"
      ],
      "correctAnswer": "30"
    },
    {
      "question": "Какой океан омывает только один материк?",
      "options": [
        "Тихий",
        "Атлантический",
        "Индийский",
        "Северный Ледовитый"
      ],
      "correctAnswer": "Северный Ледовитый"
    },
    {
      "question": "Какой элемент 'Na'?",
      "options": [
        "азот",
        "натрий",
        "неон",
        "никель"
      ],
      "correctAnswer": "натрий"
    },
    {
      "question": "Как называется график функции y = k/x?",
      "options": [
        "прямая",
        "парабола",
        "гипербола",
        "синусоида"
      ],
      "correctAnswer": "гипербола"
    },
    {
      "question": "Если вы обгоняете второго, каким вы будете?",
      "options": [
        "первым",
        "вторым",
        "третьим",
        "последним"
      ],
      "correctAnswer": "вторым"
    },
    {
      "question": "В каком слове ударение на первом слоге?",
      "options": [
        "звонит",
        "портфель",
        "алфавит",
        "средства"
      ],
      "correctAnswer": "средства"
    },
    {
      "question": "Кто погиб на дуэли в 1837 году?",
      "options": [
        "Лермонтов",
        "Пушкин",
        "Некрасов",
        "Тютчев"
      ],
      "correctAnswer": "Пушкин"
    },
    {
      "question": "Река — символ России?",
      "options": [
        "Дон",
        "Волга",
        "Обь",
        "Лена"
      ],
      "correctAnswer": "Волга"
    },
    {
      "question": "Какой частью речи является 'вокруг' в предложении 'Ходить вокруг дома'?",
      "options": [
        "существительное",
        "наречие",
        "предлог",
        "прилагательное"
      ],
      "correctAnswer": "предлог"
    },
    {
      "question": "Какой орган фильтрует кровь?",
      "options": [
        "печень",
        "почки",
        "лёгкие",
        "сердце"
      ],
      "correctAnswer": "почки"
    }
  ]
}