{
  "quiz": [
    {
      "question": "В каком предложении есть деепричастный оборот?",
      "options": [
        "Он шёл домой.",
        "Он шёл, напевая.",
        "Он усталый.",
        "Он любит петь."
      ],
      "correctAnswer": "Он шёл, напевая."
    },
    {
      "question": "Какой знак нужно поставить между 2 и 3, чтобы получить число больше 2, но меньше 3?",
      "options": [
        ",",
        ".",
        "+",
        "-"
      ],
      "correctAnswer": ","
    },
    {
      "question": "Какой тип данных неизменяем?",
      "options": [
        "list",
        "dict",
        "set",
        "tuple"
      ],
      "correctAnswer": "tuple"
    },
    {
      "question": "Какой тип данных для целых чисел в Python?",
      "options": [
        "float",
        "str",
        "bool",
        "int"
      ],
      "correctAnswer": "int"
    },
    {
      "question": "Чему равен НОД(24, 36)?",
      "options": [
        "6",
        "12",
        "18",
        "24"
      ],
      "correctAnswer": "12"
    },
    {
      "question": "Река — символ России?",
      "options": [
        "Дон",
        "Волга",
        "Обь",
        "Лена"
      ],
      "correctAnswer": "Волга"
    },
    {
      "question": "Какой элемент обозначается 'C'?",
      "options": [
        "кальций",
        "хлор",
        "углерод",
        "медь"
      ],
      "correctAnswer": "углерод"
    },
    {
      "question": "Столица Канады?",
      "options": [
        "Торонто",
        "Ванкувер",
        "Оттава",
        "Монреаль"
      ],
      "correctAnswer": "Оттава"
    },
    {
      "question": "Столица Австралии?",
      "options": [
        "Сидней",
        "Мельбурн",
        "Канберра",
        "Брисбен"
      ],
      "correctAnswer": "Канберра"
    },
    {
      "question": "Можно ли разделить 5 яблок между 5 людьми так, чтобы одно осталось в корзине?",
      "options": [
        "нет",
        "да, если одно отдать с корзиной",
        "только если резать",
        "невозможно"
      ],
      "correctAnswer": "да, если одно отдать с корзиной"
    },
    {
      "question": "Как называются организмы, создающие органику из неорганики?",
      "options": [
        "гетеротрофы",
        "автотрофы",
        "сапрофиты",
        "паразиты"
      ],
      "correctAnswer": "автотрофы"
    },
    {
      "question": "Как звали собаку в 'Муму'?",
      "options": [
        "Милка",
        "Муму",
        "Жучка",
        "Белка"
      ],
      "correctAnswer": "Муму"
    },
    {
      "question": "Какой витамин предотвращает цингу?",
      "options": [
        "A",
        "B",
        "C",
        "D"
      ],
      "correctAnswer": "C"
    },
    {
      "question": "Какой язык для клиентской веб-разработки?",
      "options": [
        "Python",
        "Java",
        "JavaScript",
        "C++"
      ],
      "correctAnswer": "JavaScript"
    },
    {
      "question": "Самая высокая гора в мире?",
      "options": [
        "Эльбрус",
        "Килиманджаро",
        "Эверест",
        "Монблан"
      ],
      "correctAnswer": "Эверест"
    }
  ]
}